chronotui/__init__.py
chronotui/__main__.py
chronotui/app.py
chronotui/stopwatch.tcss
chronotui/config/defaults.py
chronotui/widgets/confirm_screen.py
chronotui/widgets/settings_screen.py
chronotui/widgets/stopwatch.py
chronotui/widgets/time_display.py
chronotui-0.4.0.dist-info/METADATA
chronotui-0.4.0.dist-info/WHEEL
chronotui-0.4.0.dist-info/entry_points.txt
chronotui-0.4.0.dist-info/top_level.txt
chronotui-0.4.0.dist-info/RECORD
