Metadata-Version: 2.4
Name: chronotui
Version: 0.4.0
Summary: Python TUI with Textual for tracking time 
Author-email: Šimon Růžička <simon.ruzicka@protonmail.com>, Filip Špelina <filip.spelina@proton.me>
Project-URL: Homepage, https://github.com/ruzicka02/chronotui
Project-URL: Repository, https://github.com/ruzicka02/chronotui.git
Requires-Python: >=3.10
Requires-Dist: platformdirs>=4.3.8
Requires-Dist: textual>=3.7.1
